setup.py
ec2_scheduler/__init__.py
ec2_scheduler/main.py
ec2_scheduler.egg-info/PKG-INFO
ec2_scheduler.egg-info/SOURCES.txt
ec2_scheduler.egg-info/dependency_links.txt
ec2_scheduler.egg-info/entry_points.txt
ec2_scheduler.egg-info/not-zip-safe
ec2_scheduler.egg-info/requires.txt
ec2_scheduler.egg-info/top_level.txt