Metadata-Version: 1.0
Name: ec2-scheduler
Version: 0.1
Summary: Schedule stop & start of ec2 instances
Home-page: UNKNOWN
Author: Padmakar Ojha
Author-email: padmakarojha@snapdeal.com
License: GPL-3.0
Keywords: ec2 cost optimization
Platform: UNKNOWN
